MANIFEST.in
README.md
requirements.txt
setup.py
pwbm_api/__init__.py
pwbm_api/client.py
pwbm_api/constants.py
pwbm_api/filters.py
pwbm_api/response.py
pwbm_api/sorting.py
pwbm_api/entities/__init__.py
pwbm_api/entities/base.py
pwbm_api/entities/date_range.py
pwbm_api/entities/modification.py
pwbm_api/entities/page_info.py
pwbm_api/entities/query.py
pwbm_api/entities/query_params.py
pwbm_api/entities/search_meta.py
pwbm_api/entities/series_line_attributes.py
pwbm_api/entities/series_tag.py
pwbm_api/entities/series_value.py
pwbm_api/entities/source.py
pwbm_api/entities/table.py
pwbm_api/entities/tag.py
pwbm_api/entities/tags.py
pwbm_api/query/__init__.py
pwbm_api/query/base.py
pwbm_api/query/series.py
pwbm_api/query/tables.py
pwbm_api/representations/__init__.py
pwbm_api/representations/series.py
pwbm_api/representations/tables.py
pwbm_api_client.egg-info/PKG-INFO
pwbm_api_client.egg-info/SOURCES.txt
pwbm_api_client.egg-info/dependency_links.txt
pwbm_api_client.egg-info/requires.txt
pwbm_api_client.egg-info/top_level.txt