Metadata-Version: 2.1
Name: pwbm-api-client
Version: 0.9.58
Summary: UNKNOWN
Home-page: UNKNOWN
License: UNKNOWN
Platform: UNKNOWN
Requires-Python: >=3.8
